{
  "name": "Breadcrumb",
  "description": "显示网站的层级结构，告知用户当前所在位置，以及在需要向上级导航时使用。",
  "description_zh": "显示网站的层级结构，告知用户当前所在位置，以及在需要向上级导航时使用。",
  "tag": "面包屑",
  "props": {
    "separator": {
      "default": "/",
      "value": "",
      "type": "String | Element String",
      "description": "自定义分隔符",
      "isRequired": false,
      "description_zh": "自定义分隔符"
    }
  },
  "link": "https://www.iviewui.com/view-ui-plus/component/navigation/breadcrumb",
  "link_zh": "https://www.iviewui.com/view-ui-plus/component/navigation/breadcrumb",
  "typeDetail": {},
  "events": [],
  "methods": [],
  "slots": [],
  "filename": "Breadcrumb",
  "suggestions": [
    "BreadcrumbItem"
  ]
}
