{
  "name": "UniLink",
  "typeDetail": {},
  "link": "https://uniapp.dcloud.net.cn/component/uniui/uni-link.html",
  "link_zh": "https://uniapp.dcloud.net.cn/component/uniui/uni-link.html",
  "filename": "Link",
  "slots": [
    {
      "name": "default",
      "description": "自定义内容，会覆盖原有的内容显示（仅 vue 支持）",
      "description_zh": "自定义内容，会覆盖原有的内容显示（仅 vue 支持）"
    }
  ],
  "methods": [],
  "events": [],
  "props": {
    "href": {
      "type": "String",
      "value": "",
      "default": "-",
      "description": "链接地址",
      "description_zh": "链接地址",
      "required": true
    },
    "text": {
      "type": "String",
      "value": "",
      "default": "-",
      "description": "显示文字",
      "description_zh": "显示文字",
      "required": true
    },
    "download": {
      "type": "String",
      "value": "",
      "default": "-",
      "description": "H5平台下载文件名",
      "description_zh": "H5平台下载文件名"
    },
    "showUnderLine": {
      "type": "Boolean",
      "value": "",
      "default": "true",
      "description": "是否显示下划线",
      "description_zh": "是否显示下划线"
    },
    "copyTips": {
      "type": "String",
      "value": "",
      "default": "已自动复制网址，请在手机浏览器里粘贴该网址",
      "description": "在小程序端复制链接时的提示语",
      "description_zh": "在小程序端复制链接时的提示语"
    },
    "color": {
      "type": "String",
      "value": "",
      "default": "#999999",
      "description": "链接文字颜色",
      "description_zh": "链接文字颜色"
    },
    "fontSize": {
      "type": "String",
      "value": "",
      "default": "14",
      "description": "链接文字大小，单位px",
      "description_zh": "链接文字大小，单位px"
    }
  },
  "suggestions": [],
  "description": "uni-link是一个外部网页超链接组件，在小程序内复制url，在app内打开外部浏览器，在h5端打开新网页。",
  "description_zh": "uni-link是一个外部网页超链接组件，在小程序内复制url，在app内打开外部浏览器，在h5端打开新网页。"
}
