{
  "name": "RangePicker",
  "props": {
    "allowEmpty": {
      "value": "",
      "description": "允许起始项部分为空",
      "default": "[false, false]",
      "type": "[boolean, boolean]"
    },
    "dateRender": {
      "value": "",
      "description": "自定义日期单元格的内容，5.4.0 起用 `cellRender` 代替",
      "default": "-",
      "type": "function(currentDate: dayjs, today: dayjs) => React.ReactNode"
    },
    "cellRender": {
      "value": "",
      "description": "自定义单元格的内容。",
      "default": "-",
      "type": "(current: dayjs, info: { originNode: React.ReactElement,today: DateType, range?: 'start' | 'end', type: PanelMode, locale?: Locale, subType?: 'hour' | 'minute' | 'second' | 'meridiem' }) => React.ReactNode"
    },
    "defaultPickerValue": {
      "value": "",
      "description": "默认面板日期",
      "default": "-",
      "type": "[dayjs]"
    },
    "defaultValue": {
      "value": "",
      "description": "默认日期",
      "default": "-",
      "type": "[dayjs]"
    },
    "disabled": {
      "value": "",
      "description": "禁用起始项",
      "default": "-",
      "type": "[boolean, boolean]"
    },
    "disabledTime": {
      "value": "",
      "description": "不可选择的时间",
      "default": "-",
      "type": "function(date: dayjs, partial: `start` | `end`)"
    },
    "format": {
      "value": "",
      "description": "展示的日期格式",
      "default": "`YYYY-MM-DD HH:mm:ss`",
      "type": "[formatType]"
    },
    "presets": {
      "value": "",
      "description": "预设时间范围快捷选择",
      "default": "-",
      "type": "{ label: React.ReactNode, value: [dayjs]}"
    },
    "renderExtraFooter": {
      "value": "",
      "description": "在面板中添加额外的页脚",
      "default": "-",
      "type": "() => React.ReactNode"
    },
    "separator": {
      "value": ["`<SwapRightOutlined />`"],
      "description": "设置分隔符",
      "default": "`<SwapRightOutlined />`",
      "type": "React.ReactNode"
    },
    "showTime": {
      "value": ["[TimePicker Options]"],
      "description": "增加时间选择功能",
      "default": "[TimePicker Options]",
      "type": "Object | boolean"
    },
    "showTime.defaultValue": {
      "value": "",
      "description": "设置用户选择日期时默认的时分秒",
      "default": "[dayjs(), dayjs()]",
      "type": "[dayjs]"
    },
    "value": {
      "value": "",
      "description": "日期",
      "default": "-",
      "type": "[dayjs]"
    }
  },
  "methods": [],
  "events": [
    {
      "name": "onCalendarChange",
      "description": "待选日期发生变化的回调。`info` 参数自 4.4.0 添加",
      "params": "function(dates: [dayjs, dayjs], dateStrings: [string, string], info: { range:`start`|`end` })"
    },
    {
      "name": "onChange",
      "description": "日期范围发生变化的回调",
      "params": "function(dates: [dayjs, dayjs], dateStrings: [string, string])"
    }
  ],
  "link": "http://192.168.119.22:8001/components/date-picker"
}
