{
  "name": "Scroll.Root",
  "props": {
    "asChild": {
      "value": "",
      "required": false,
      "default": "false",
      "type": "boolean",
      "description": "",
      "description_zh": ""
    },
    "type": {
      "value": "",
      "required": false,
      "default": "hover",
      "type": "enumSee",
      "description": "",
      "description_zh": ""
    },
    "scrollHideDelay": {
      "value": "",
      "required": false,
      "default": "600",
      "type": "number",
      "description": "",
      "description_zh": ""
    },
    "dir": {
      "value": "",
      "required": false,
      "default": "No default value",
      "type": "enumSee",
      "description": "",
      "description_zh": ""
    },
    "nonce": {
      "value": "",
      "required": false,
      "default": "No default value",
      "type": "string",
      "description": "",
      "description_zh": ""
    }
  },
  "description": "Contains all the parts of a scroll area.",
  "link": "https://www.radix-ui.com/primitives/docs/components/scroll-area",
  "link_zh": "https://www.radix-ui.com/primitives/docs/components/scroll-area",
  "typeDetail": {},
  "events": [],
  "methods": [],
  "slots": [],
  "filename": "ScrollRoot",
  "suggestions": []
}
