{
  "name": "NBreadcrumb",
  "props": {
    "separator": {
      "description": "面包屑之间的分隔符",
      "description_zh": "面包屑之间的分隔符",
      "default": "/",
      "value": "",
      "type": "string",
      "required": false
    }
  },
  "events": [],
  "methods": [],
  "slots": [
    {
      "name": "default",
      "description": "Breadcrumb 默认填充的内容",
      "description_zh": "Breadcrumb 默认填充的内容"
    }
  ],
  "suggestions": [
    "n-breadcrumb-item"
  ],
  "link": "https://www.naiveui.com/zh-CN/os-theme/components/breadcrumb#Breadcrumb-Item-Slots",
  "link_zh": "https://www.naiveui.com/zh-CN/os-theme/components/breadcrumb#Breadcrumb-Item-Slots",
  "filename": "Breadcrumb",
  "typeDetail": {}
}
