{
  "name": "NMention",
  "props": {
    "autosize": {
      "value": "",
      "description": "自动换行",
      "default": "false",
      "type": "boolean | { maxRows?: number, minRows?: number }"
    },
    "options": {
      "value": "",
      "description": "选项列表",
      "default": "[]",
      "type": "MentionOption[]"
    },
    "type": {
      "value": "",
      "description": "输入框类型",
      "default": "'text'",
      "type": "'text' | 'textarea'"
    },
    "separator": {
      "value": "",
      "description": "切分提及使用的字符，长度必须为 1",
      "default": "' '",
      "type": "string"
    },
    "bordered": {
      "value": "",
      "description": "是否显示输入框边框",
      "default": "true",
      "type": "boolean"
    },
    "disabled": {
      "value": "",
      "description": "是否设置输入框为禁用状态",
      "default": "false",
      "type": "boolean"
    },
    "value": {
      "value": "",
      "description": "输入框的值",
      "default": "undefined",
      "type": "string | null"
    },
    "default-value": {
      "value": "",
      "description": "输入框的默认值",
      "default": "''",
      "type": "string"
    },
    "loading": {
      "value": "",
      "description": "选择面板是否显示加载状态",
      "default": "false",
      "type": "boolean"
    },
    "prefix": {
      "value": "",
      "description": "触发提及的前缀，长度必须为 1",
      "default": "'@'",
      "type": "string | string[]"
    },
    "placeholder": {
      "value": "",
      "description": "输入框的占位符",
      "default": "''",
      "type": "string"
    },
    "placement": {
      "value": "",
      "description": "选择面板的弹出位置.",
      "default": "'bottom-start'",
      "type": "'top-start' | 'top' | 'top-end' | 'right-start' | 'right' | 'right-end' | 'bottom-start' | 'bottom' | 'bottom-end' | 'left-start' | 'left' | 'left-end'"
    },
    "render-label": {
      "value": "",
      "description": "选项标签渲染函数",
      "default": "undefined",
      "type": "(option: MentionOption) => VNodeChild"
    },
    "size": {
      "value": "",
      "description": "输入框的大小",
      "default": "'medium'",
      "type": "'small' | 'medium' | 'large'"
    },
    "status": {
      "value": "",
      "description": "验证状态",
      "default": "undefined",
      "type": "'success' | 'warning' | 'error'"
    },
    "to": {
      "value": "",
      "description": "菜单的容器节点，`false` 会待在原地",
      "default": "body",
      "type": "string | HTMLElement | false"
    }
  },
  "methods": [
    {
      "name": "focus",
      "description": "`() => void`",
      "params": "聚焦"
    },
    {
      "name": "blur",
      "description": "`() => void`",
      "params": "失焦"
    }
  ],
  "typeDetail": {
    "MentionOption": [
      {
        "name": "class",
        "description": "选项的自定义类名",
        "type": "`string`"
      },
      {
        "name": "disabled",
        "description": "选项是否禁用",
        "type": "`boolean`"
      },
      {
        "name": "label",
        "description": "选项的标签",
        "type": "`string | (option: MentionOption) => VNodeChild`"
      },
      {
        "name": "render",
        "description": "支持通过 `render` 渲染函数自定义选项",
        "type": "`(option: MentionOption) => VNodeChild`"
      },
      {
        "name": "style",
        "description": "选项的样式",
        "type": "`string`"
      },
      {
        "name": "value",
        "description": "在选项中应该是唯一的",
        "type": "`string`"
      }
    ]
  },
  "events": [
    {
      "name": "update:show",
      "description": "选择面板显示状态发生变化时触发",
      "params": "`(show: boolean) => void`"
    },
    {
      "name": "update:value",
      "description": "输入框值发生更新时触发",
      "params": "`(value: string) => void`"
    },
    {
      "name": "select",
      "description": "输入框的选中时触发",
      "params": "`(option: MentionOption, prefix: string) => void`"
    },
    {
      "name": "focus",
      "description": "输入框获得焦点时触发",
      "params": "`(e: FocusEvent) => void`"
    },
    {
      "name": "search",
      "description": "输入框搜索时触发",
      "params": "`(pattern: string, prefix: string) => void`"
    },
    {
      "name": "blur",
      "description": "输入框失去焦点时触发",
      "params": "`(e: FocusEvent) => void`"
    }
  ],
  "link": "https://www.naiveui.com/zh-CN/dark/components/mention"
}
