{
  "name": "Breadcrumb",
  "props": {
    "itemRender": {
      "value": "",
      "description": "自定义链接函数，和 react-router 配置使用",
      "default": "-",
      "type": "(route, params, routes, paths) => ReactNode"
    },
    "params": {
      "value": "",
      "description": "路由的参数",
      "default": "-",
      "type": "object"
    },
    "items": {
      "value": "",
      "description": "路由栈信息",
      "default": "-",
      "type": "items[]"
    },
    "separator": {
      "value": "",
      "description": "分隔符自定义",
      "default": "/",
      "type": "ReactNode"
    }
  },
  "typeDetail": {
    "ItemType": [
      { "name": "className", "description": "自定义类名", "type": "string" },
      { "name": "dropdownProps", "description": "弹出下拉菜单的自定义配置", "type": "[Dropdown]" },
      { "name": "href", "description": "链接的目的地，不能和 path 共用", "type": "string" },
      { "name": "path", "description": "拼接路径，每一层都会拼接前一个 path 信息。不能和 href 共用", "type": "string" },
      { "name": "menu", "description": "菜单配置项", "type": "[MenuProps]" },
      { "name": "title", "description": "名称", "type": "ReactNode" },
      { "name": "onClick", "description": "单击事件", "callback": "(e:MouseEvent) => void" }
    ]
  },
  "events": [],
  "link": "https://ant.design/components//breadcrumb"
}
