{
  "name": "VDatePickerControls",
  "props": {
    "active": {
      "default": "undefined",
      "value": "",
      "type": "string | string[]",
      "description": "Controls the active state of the item. This is typically used to highlight the component.",
      "description_zh": "控制项的活动状态。这通常用于突出显示组件。"
    },
    "disabled": {
      "default": "false",
      "value": "",
      "type": "string | boolean | string[]",
      "description": "Removes the ability to click or target the component.",
      "description_zh": "删除了单击组件或将组件定位的功能。"
    },
    "mode-icon": {
      "default": "$subgroup",
      "value": "",
      "type": "string",
      "description": "MISSING DESCRIPTION (edit in github)",
      "description_zh": "缺少描述（在 github 中编辑）"
    },
    "next-icon": {
      "default": "$next",
      "value": "",
      "type": "string",
      "description": "MISSING DESCRIPTION (edit in github)",
      "description_zh": "缺少描述（在 github 中编辑）"
    },
    "prev-icon": {
      "default": "$prev",
      "value": "",
      "type": "string",
      "description": "MISSING DESCRIPTION (edit in github)",
      "description_zh": "缺少描述（在 github 中编辑）"
    },
    "text": {
      "default": "undefined",
      "value": "",
      "type": "string",
      "description": "Specify content text for the component.",
      "description_zh": "指定组件的内容文本。"
    },
    "view-mode": {
      "default": "month",
      "value": "",
      "type": "month / months / year",
      "description": "MISSING DESCRIPTION (edit in github)",
      "description_zh": "缺少描述（在 github 中编辑）"
    }
  },
  "link": "https://vuetifyjs.com/en/api/v-date-picker-controls/#props",
  "link_zh": "https://vuetifyjs.com/en/api/v-date-picker-controls/#props",
  "typeDetail": {},
  "events": [
    {
      "name": "click:month",
      "description": "MISSING DESCRIPTION (edit in github)",
      "description_zh": "缺少描述（在 github 中编辑）",
      "params": "[]",
      "value": ""
    },
    {
      "name": "click:next",
      "description": "MISSING DESCRIPTION (edit in github)",
      "description_zh": "缺少描述（在 github 中编辑）",
      "params": "[]",
      "value": ""
    },
    {
      "name": "click:prev",
      "description": "MISSING DESCRIPTION (edit in github)",
      "description_zh": "缺少描述（在 github 中编辑）",
      "params": "[]",
      "value": ""
    },
    {
      "name": "click:text",
      "description": "MISSING DESCRIPTION (edit in github)",
      "description_zh": "缺少描述（在 github 中编辑）",
      "params": "[]",
      "value": ""
    },
    {
      "name": "click:year",
      "description": "MISSING DESCRIPTION (edit in github)",
      "description_zh": "缺少描述（在 github 中编辑）",
      "params": "[]",
      "value": ""
    }
  ],
  "methods": [],
  "slots": [
    {
      "name": "default",
      "description": "The default Vue slot.",
      "description_zh": "默认的 Vue 插槽。"
    }
  ]
}
