{
  "name": "AccordionItem",
  "props": {
    "id": {
      "type": "string",
      "required": false,
      "description": "A unique id for the accordion item."
    },
    "isDisabled": {
      "type": "boolean",
      "default": false,
      "required": false,
      "description": "If `true`, the accordion item will be disabled."
    },
    "isFocusable": {
      "type": "boolean",
      "default": false,
      "required": false,
      "description": "If `true`, the accordion item will be focusable."
    }
  },
  "methods": [],
  "typeDetail": {},
  "events": [],
  "link": "https://vant-docs.netlify.app/#/zh-CN/action-bar%23zi-ding-yi-an-niu-yan-se"
}
