{
  "name": "PinInputRoot",
  "props": {
    "as": {
      "default": "div",
      "value": "",
      "type": "string | Component",
      "description": "The element or component the current element should render as.",
      "description_zh": "当前元素应呈现为的元素或组件。"
    },
    "asChild": {
      "default": "false",
      "value": "",
      "type": "boolean",
      "description": "Change the default rendered element for the one passed as a child, merging their props and behavior.",
      "description_zh": "更改作为子元素传递的默认渲染元素，合并其道具和行为。"
    },
    "defaultValue": {
      "default": "",
      "value": "",
      "type": "string[]",
      "description": "The default value of the input.",
      "description_zh": "输入的默认值。"
    },
    ":v-model": {
      "default": "",
      "value": "",
      "type": "string[]",
      "description": "The value of the input.",
      "description_zh": "输入的值。",
      "required": true
    },
    "placeholder": {
      "default": "",
      "value": "",
      "type": "string",
      "description": "The placeholder of the input.",
      "description_zh": "输入的占位符。",
      "required": true
    },
    "mask": {
      "default": "false",
      "value": "",
      "type": "boolean",
      "description": "When true, pin inputs will be treated as password.",
      "description_zh": "当为true时，引脚输入将被视为密码。"
    },
    "otp": {
      "default": "false",
      "value": "",
      "type": "boolean",
      "description": "When true, mobile devices will autodetect the OTP from messages or clipboard, and enable the autocomplete field.",
      "description_zh": "为真时，移动设备将从信息或剪贴板中自动检测 OTP，并启用自动完成字段。"
    },
    "type": {
      "default": "text",
      "value": "",
      "type": "text | number",
      "description": "Input type for the inputs.",
      "description_zh": "输入的输入类型。"
    },
    "disabled": {
      "default": "false",
      "value": "",
      "type": "boolean",
      "description": "When true, the input will be disabled.",
      "description_zh": "为真时，输入将被禁用。"
    },
    "required": {
      "default": "false",
      "value": "",
      "type": "boolean",
      "description": "When true, the input will be required.",
      "description_zh": "为真时，输入将被要求。"
    },
    "name": {
      "default": "",
      "value": "",
      "type": "string",
      "description": "The name of the input.",
      "description_zh": "输入的名称。"
    }
  },
  "events": [
    {
      "name": "update:modelValue",
      "params": "(value: string[]) => void",
      "description": "Event handler called when the value state of the pin input changes.",
      "description_zh": "当引脚输入的值状态改变时调用的事件处理程序。",
      "value": ""
    },
    {
      "name": "complete",
      "params": "(value: string[]) => void",
      "description": "Event handler called the inputs were filled.",
      "description_zh": "事件处理程序调用输入被填充。",
      "value": ""
    }
  ],
  "methods": [],
  "suggestions": [
    "PinInputInput"
  ],
  "link": "https://www.radix-vue.com/utilities/pin-input.html",
  "link_zh": "https://www.radix-vue.com/utilities/pin-input.html"
}
