{
  "name": "VarLink",
  "props": {
    "type": {
      "description": "Link type, can be set to default primary info success warning danger",
      "description_zh": "Link type, can be set to default primary info success warning danger",
      "default": "default",
      "value": "",
      "type": "string"
    },
    "underline": {
      "description": "Underline, Can be set to always hover none",
      "description_zh": "Underline, Can be set to always hover none",
      "default": "always",
      "value": "",
      "type": "string"
    },
    "disabled": {
      "description": "Whether to disable link",
      "description_zh": "Whether to disable link",
      "default": "false",
      "value": "",
      "type": "boolean"
    },
    "text-color": {
      "description": "Link text color",
      "description_zh": "Link text color",
      "default": "-",
      "value": "",
      "type": "string"
    },
    "text-size": {
      "description": "Link font size",
      "description_zh": "Link font size",
      "default": "-",
      "value": "",
      "type": "string | number"
    },
    "href": {
      "description": "Same as native hyperlink's href, Have higher priority than to",
      "description_zh": "Same as native hyperlink's href, Have higher priority than to",
      "default": "-",
      "value": "",
      "type": "string"
    },
    "rel": {
      "description": "Same as the native rel attribute",
      "description_zh": "Same as the native rel attribute",
      "default": "-",
      "value": "",
      "type": "string"
    },
    "target": {
      "description": "Same as the native target attribute",
      "description_zh": "Same as the native target attribute",
      "default": "-",
      "value": "",
      "type": "string"
    },
    "to": {
      "description": "router-link to, will render as <router-link />",
      "description_zh": "router-link to, will render as <router-link />",
      "default": "-",
      "value": "",
      "type": "string | object"
    },
    "replace": {
      "description": "router-link replace",
      "description_zh": "router-link replace",
      "default": "false",
      "value": "",
      "type": "boolean"
    }
  },
  "link": "https://varlet.gitee.io/varlet-ui/#/en-US/link",
  "link_zh": "https://varlet.gitee.io/varlet-ui/#/en-US/link",
  "typeDetail": {},
  "events": [
    {
      "name": "click",
      "description": "Triggered when the link is clicked",
      "description_zh": "Triggered when the link is clicked",
      "params": "event: Event"
    }
  ],
  "methods": [],
  "slots": [
    {
      "name": "default",
      "description": "Link content",
      "description_zh": "Link content"
    }
  ]
}
