{
  "name": "Switch",
  "props": {
    "checked": {
      "default": "false",
      "value": "",
      "type": "boolean",
      "description": "Whether the switch is on",
      "description_zh": "开关是否打开"
    },
    "defaultChecked": {
      "default": "false",
      "value": "",
      "type": "boolean",
      "description": "Default is selected",
      "description_zh": "默认是否选中"
    },
    "disabled": {
      "default": "false",
      "value": "",
      "type": "boolean",
      "description": "Whether to disable or not",
      "description_zh": "是否禁用"
    },
    "loading": {
      "default": "false",
      "value": "",
      "type": "boolean",
      "description": "Loading",
      "description_zh": "加载中状态"
    },
    "size": {
      "default": "-",
      "value": [
        "small",
        "default"
      ],
      "type": "small / default",
      "description": "The size of the switch is available in small and default.",
      "description_zh": "开关的尺寸，有 small 和 default 可供选择。"
    },
    "type": {
      "default": "circle",
      "value": [
        "circle",
        "round",
        "line"
      ],
      "type": "circle / round / line",
      "description": "Three style types",
      "description_zh": "三种样式类型"
    },
    ":checkedIcon": {
      "default": "-",
      "value": "",
      "type": "ReactNode",
      "description": "The icon that appears on the button when the switch is on",
      "description_zh": "开关打开时，按钮上显示的图标"
    },
    ":checkedText": {
      "default": "-",
      "value": "",
      "type": "ReactNode",
      "description": "When the switch is turned on, the small size does not take effect.",
      "description_zh": "开关打开时的文案，small 尺寸不生效。"
    },
    ":uncheckedIcon": {
      "default": "-",
      "value": "",
      "type": "ReactNode",
      "description": "The icon that appears on the button when the switch is off",
      "description_zh": "开关关闭时，按钮上显示的图标"
    },
    ":uncheckedText": {
      "default": "-",
      "value": "",
      "type": "ReactNode",
      "description": "When the switch is off, the small size does not take effect.",
      "description_zh": "开关关闭时的文案，small 尺寸不生效。"
    },
    "className": {
      "default": "-",
      "value": "",
      "type": "string | string[]",
      "description": "Node class name",
      "description_zh": "节点类名"
    },
    ":style": {
      "default": "-",
      "value": "",
      "type": "CSSProperties",
      "description": "Node style",
      "description_zh": "节点样式"
    }
  },
  "methods": [],
  "link": "https://arco.design/react/components/switch#api",
  "link_zh": "https://arco.design/react/components/switch#api",
  "events": [
    {
      "name": "onChange",
      "description": "Click the callback of the switch",
      "description_zh": "点击开关的回调",
      "params": "(value: boolean, event) => void",
      "value": ""
    }
  ],
  "typeDetail": {}
}
