{
  "name": "USlider",
  "props": {
    "v-model": {
      "description": "双向绑定滑块选择值",
      "description_zh": "双向绑定滑块选择值",
      "default": "0",
      "value": "",
      "type": "String | Number"
    },
    "min": {
      "description": "可选的最小值(0-100之间)",
      "description_zh": "可选的最小值(0-100之间)",
      "default": "0",
      "value": "",
      "type": "String | Number"
    },
    "max": {
      "description": "可选的最大值(0-100之间)",
      "description_zh": "可选的最大值(0-100之间)",
      "default": "100",
      "value": "",
      "type": "String | Number"
    },
    "step": {
      "description": "选择的步长",
      "description_zh": "选择的步长",
      "default": "1",
      "value": "",
      "type": "String | Number"
    },
    "block-width": {
      "description": "滑动按钮的宽度(高等于宽)，单位rpx",
      "description_zh": "滑动按钮的宽度(高等于宽)，单位rpx",
      "default": "30",
      "value": "",
      "type": "String | Number"
    },
    "height": {
      "description": "滑动选择条的高度，单位rpx",
      "description_zh": "滑动选择条的高度，单位rpx",
      "default": "6",
      "value": "",
      "type": "String | Number"
    },
    "inactive-color": {
      "description": "滑动选择条的底部背景颜色",
      "description_zh": "滑动选择条的底部背景颜色",
      "default": "#c0c4cc",
      "value": "",
      "type": "String"
    },
    "active-color": {
      "description": "底部选择部分的背景颜色",
      "description_zh": "底部选择部分的背景颜色",
      "default": "#2979ff",
      "value": "",
      "type": "String"
    },
    "block-color": {
      "description": "滑块背景颜色",
      "description_zh": "滑块背景颜色",
      "default": "#ffffff",
      "value": "",
      "type": "String"
    },
    "block-style": {
      "description": "给滑块按钮自定义样式，对象形式",
      "description_zh": "给滑块按钮自定义样式，对象形式",
      "default": "-",
      "value": "",
      "type": "Object"
    },
    "disabled": {
      "description": "是否禁用滑块",
      "description_zh": "是否禁用滑块",
      "default": "false",
      "value": "",
      "type": "Boolean"
    },
    "use-slot": {
      "description": "是否使用slot传入自定义滑块",
      "description_zh": "是否使用slot传入自定义滑块",
      "default": "false",
      "value": "",
      "type": "Boolean"
    }
  },
  "link": "https://v1.uviewui.com/components/slider.html",
  "link_zh": "https://v1.uviewui.com/components/slider.html",
  "typeDetail": {},
  "events": [],
  "methods": [],
  "slots": []
}
