{
  "name": "WdCurtain",
  "props": {
    "value": {
      "default": "",
      "value": "-",
      "type": "boolean",
      "description": "Bind a value to show/close the curtain",
      "version": "-",
      "required": false,
      "description_zh": "绑定值，展示/关闭幕帘"
    },
    "src": {
      "default": "",
      "value": "-",
      "type": "string",
      "description": "curtain picture address, must use a network address",
      "version": "-",
      "required": false,
      "description_zh": "幕帘图片地址，必须使用网络地址"
    },
    "width": {
      "default": "",
      "value": "-",
      "type": "number",
      "description": "Curtain image width, default unit px",
      "version": "-",
      "required": false,
      "description_zh": "幕帘图片宽度，默认单位px"
    },
    "to": {
      "default": "",
      "value": "-",
      "type": "string",
      "description": "Curtain pictures click on the link",
      "version": "-",
      "required": false,
      "description_zh": "幕帘图片点击链接"
    },
    "close-position": {
      "default": "",
      "value": "inset",
      "type": "inset / top / bottom / top-left / top-right / bottom-left / bottom-right",
      "description": "Turn off the button position",
      "version": "-",
      "required": false,
      "description_zh": "关闭按钮位置"
    },
    "close-on-click-modal": {
      "default": "",
      "value": "false",
      "type": "boolean",
      "description": "Click whether the mask is off",
      "version": "-",
      "required": false,
      "description_zh": "点击遮罩是否关闭"
    },
    "hide-when-close": {
      "default": "",
      "value": "true",
      "type": "boolean",
      "description": "是否当关闭时将弹出层隐藏（display: none)",
      "version": "-",
      "required": false,
      "description_zh": "是否当关闭时将弹出层隐藏（display: none)"
    }
  },
  "link": "https://wot-design-uni.pages.dev/component/curtain.html",
  "link_zh": "https://wot-design-uni.pages.dev/component/curtain.html",
  "typeDetail": {},
  "events": [
    {
      "name": "click",
      "description": "Triggered when the curtain is tapped",
      "params": "-",
      "version": "-",
      "value": "",
      "description_zh": "点击幕帘时触发"
    },
    {
      "name": "close",
      "description": "Triggered when the pop-up layer is closed",
      "params": "-",
      "version": "-",
      "value": "",
      "description_zh": "弹出层关闭时触发"
    },
    {
      "name": "click-modal",
      "description": "Triggered when the mask is clicked",
      "params": "-",
      "version": "-",
      "value": "",
      "description_zh": "点击遮罩时触发"
    },
    {
      "name": "beforeenter",
      "description": "Triggered before entering",
      "params": "-",
      "version": "-",
      "value": "",
      "description_zh": "进入前触发"
    },
    {
      "name": "enter",
      "description": "Triggered upon entry",
      "params": "-",
      "version": "-",
      "value": "",
      "description_zh": "进入时触发"
    },
    {
      "name": "afterenter",
      "description": "Triggered upon entry",
      "params": "-",
      "version": "-",
      "value": "",
      "description_zh": "进入后触发"
    },
    {
      "name": "beforeleave",
      "description": "Triggered before leaving",
      "params": "-",
      "version": "-",
      "value": "",
      "description_zh": "离开前触发"
    },
    {
      "name": "leave",
      "description": "Triggered when leaving",
      "params": "-",
      "version": "-",
      "value": "",
      "description_zh": "离开时触发"
    },
    {
      "name": "afterleave",
      "description": "Triggered after leaving",
      "params": "-",
      "version": "-",
      "value": "",
      "description_zh": "离开后触发"
    },
    {
      "name": "load",
      "description": "The image load completion event",
      "params": "-",
      "version": "-",
      "value": "",
      "description_zh": "图片加载完成事件"
    },
    {
      "name": "error",
      "description": "Image load failure event, if the image fails to load, the curtain component will not be displayed, even if the value is set to true",
      "params": "-",
      "version": "-",
      "value": "",
      "description_zh": "图片加载失败事件，若图片加载失败，则不会展示幕帘组件，即使设置 value 为 true"
    }
  ],
  "methods": [],
  "slots": [],
  "suggestions": [],
  "filename": "Curtain"
}
